pimdb/__init__.py
pimdb/bulk.py
pimdb/command.py
pimdb/common.py
pimdb/database.py
pimdb-0.3.1.dist-info/METADATA
pimdb-0.3.1.dist-info/WHEEL
pimdb-0.3.1.dist-info/entry_points.txt
pimdb-0.3.1.dist-info/licenses/LICENSE.txt
pimdb-0.3.1.dist-info/RECORD
