Metadata-Version: 2.4
Name: pimdb
Version: 0.3.1
Summary: build a database from IMDb datasets
Project-URL: Homepage, https://github.com/roskakori/pimdb
Project-URL: Repository, https://github.com/roskakori/pimdb.git
Project-URL: Documentation, https://pimdb.readthedocs.io
Project-URL: Issue Tracker, https://github.com/roskakori/pimdb/issues
Project-URL: Changes, https://pimdb.readthedocs.io/en/latest/changes/
Author-email: Thomas Aglassinger <roskakori@users.sourceforge.net>
License-Expression: BSD-3-Clause
License-File: LICENSE.txt
Keywords: IMDB,SQL,import
Classifier: Development Status :: 4 - Beta
Classifier: Environment :: Console
Classifier: Intended Audience :: Developers
Classifier: Intended Audience :: Science/Research
Classifier: License :: OSI Approved :: BSD License
Classifier: Natural Language :: English
Classifier: Operating System :: OS Independent
Classifier: Programming Language :: Python :: 3 :: Only
Classifier: Programming Language :: Python :: 3.9
Classifier: Programming Language :: Python :: 3.10
Classifier: Programming Language :: Python :: 3.11
Classifier: Programming Language :: Python :: 3.12
Classifier: Programming Language :: Python :: 3.13
Classifier: Topic :: Scientific/Engineering :: Information Analysis
Classifier: Topic :: Software Development
Requires-Python: <4,>=3.9
Requires-Dist: psycopg2-binary~=2.9
Requires-Dist: requests==2.32.4
Requires-Dist: sqlalchemy~=1.4
